evmeter_client/__init__.py
evmeter_client/cli.py
evmeter_client/client.py
evmeter_client/config.py
evmeter_client/exceptions.py
evmeter_client/models.py
evmeter_client/parser.py
evmeter_client-3.1.0.dist-info/licenses/LICENSE
evmeter_client-3.1.0.dist-info/METADATA
evmeter_client-3.1.0.dist-info/WHEEL
evmeter_client-3.1.0.dist-info/entry_points.txt
evmeter_client-3.1.0.dist-info/top_level.txt
evmeter_client-3.1.0.dist-info/RECORD
