Metadata-Version: 2.4
Name: evmeter-client
Version: 3.1.0
Summary: Python client library for EV-Meter electric vehicle chargers via MQTT
Author: EV-Meter Integration Team
License-Expression: MIT
Project-URL: Homepage, https://github.com/yourusername/evmeter-client
Project-URL: Repository, https://github.com/yourusername/evmeter-client
Project-URL: Issues, https://github.com/yourusername/evmeter-client/issues
Project-URL: Documentation, https://github.com/yourusername/evmeter-client#readme
Keywords: mqtt,ev-charger,home-assistant,evmeter,electric-vehicle
Classifier: Development Status :: 4 - Beta
Classifier: Intended Audience :: Developers
Classifier: Operating System :: OS Independent
Classifier: Programming Language :: Python :: 3
Classifier: Programming Language :: Python :: 3.8
Classifier: Programming Language :: Python :: 3.9
Classifier: Programming Language :: Python :: 3.10
Classifier: Programming Language :: Python :: 3.11
Classifier: Programming Language :: Python :: 3.12
Classifier: Topic :: Home Automation
Classifier: Topic :: System :: Hardware
Requires-Python: >=3.8
License-File: LICENSE
Requires-Dist: aiomqtt<3.0.0,>=1.2.0
Provides-Extra: dev
Requires-Dist: pytest>=7.0.0; extra == "dev"
Requires-Dist: pytest-asyncio>=0.21.0; extra == "dev"
Requires-Dist: black>=23.0.0; extra == "dev"
Requires-Dist: ruff>=0.1.0; extra == "dev"
Requires-Dist: mypy>=1.0.0; extra == "dev"
Dynamic: license-file
